{
  "product_name": "医疗美容服务",
  "brand_name": "美贝尔",
  "brand_aliases": [
    "MEBEL",
    "美贝尔整形",
    "福州美贝尔医美",
    "福州美贝尔医疗美容",
    "美贝尔医疗美容门诊部"
  ],
  "category_local": "医美",
  "category_en": "medical cosmetology",
  "source_language": "zh",
  "market_language": "zh",
  "target_market": "domestic",
  "primary_region": "福州",
  "region_level": "city",
  "business_type": "local_service",
  "geo_probe_subject": "福州医美品牌推荐",
  "market_confidence": 1.0,
  "market_reason": "材料主要为中文，针对中国大陆市场，提供本地化的线下医疗美容服务，因此source_language和market_language为zh，target_market为domestic。业务类型为提供线下医美服务的本地机构（local_service）。虽然品牌具有全国连锁性质，但当前材料主要聚焦于福州门店的本地服务。竞争对手为福州当地其他知名医美机构，基于行业常识推断。",
  "known_competitor_hints": [
    "福州海峡美容医院",
    "福州名韩整形医院",
    "福州爱美尔医疗美容",
    "福州华仁医疗美容"
  ],
  "summary": "福州美贝尔医疗美容是一家成立于2012年的专业医美连锁品牌在福州的分支机构，提供整形美容、无创美容和皮肤美容等全方位医美服务。品牌定位高端、轻奢，拥有专业的医疗团队和完善的资质保障，致力于为求美者提供个性化、精细化的高品质塑美体验。",
  "target_audience": [
    "有整形美容及抗衰老需求的求美者",
    "追求高端、轻奢医美体验的消费者",
    "有皮肤管理及微整形需求的人群"
  ],
  "selling_points": [
    "10余年品牌历史与品质保障，全国七城连锁",
    "高端、轻奢、时尚的品牌定位",
    "凝聚国内外资深医疗团队（含皮肤科、微整科、整形外科院长）",
    "提供个性化、综合化、精细化的高品质塑美体验",
    "具备完善的医疗保障体系与正规医疗资质"
  ],
  "evidence": [
    "品牌源于2012年，已成长为中国专业医美连锁品牌",
    "迄今已在福州，苏州，南京、常州，扬州，常熟，贵阳形成魅力七连城美丽版图",
    "以“高端、轻奢、时尚”为品牌定位",
    "下设整形美容、无创美容、皮肤美容三大科室",
    "(鼓)医广【2025】第12-29-87号"
  ],
  "profile_md": "### 福州美贝尔医疗美容\n\n**品牌定位**：高端、轻奢、时尚的专业医美连锁品牌\n\n**核心服务**：\n- 整形美容\n- 无创美容（微整）\n- 皮肤美容\n\n**品牌优势**：\n- **历史悠久**：源于2012年，10余年品质保障，全国七城连锁（福州、苏州、南京等）。\n- **专业团队**：汇聚国内外资深医疗团队，涵盖皮肤科、微整科及整形外科院长等常驻大咖。\n- **高品质体验**：提供个性化、综合化、精细化的塑美服务，坚持完善的医疗保障体系。\n\n**机构信息**：\n- **服务区域**：福州市鼓楼区\n- **合规资质**：具备正规医疗广告审查证明（(鼓)医广【2025】第12-29-87号）及ICP备案，合规经营。",
  "service_scope": "local_city",
  "geo_audience": "consumer_recommendation",
  "analysis_goal": "consumer_recommendation",
  "user_market_context": {
    "service_scope": "local_city",
    "service_scope_label": "本地/城市",
    "service_region": "福州",
    "category_local": "医美",
    "geo_audience": "consumer_recommendation",
    "geo_audience_label": "C端消费者",
    "analysis_goal": "consumer_recommendation",
    "analysis_goal_label": "C端消费者",
    "market_language": "zh",
    "target_market": "domestic"
  }
}