{
  "direct_competitors": [
    {
      "brand_name": "霸王茶姬",
      "competitor_type": "national_direct",
      "reason": "主打原叶鲜奶茶与国风视觉，与沈茶的“草本、国风”定位高度重合，在福州市场有强烈的直接竞争。（基于行业常识推断）"
    },
    {
      "brand_name": "茶百道",
      "competitor_type": "national_direct",
      "reason": "拥有“豆乳玉麒麟”等豆乳/豆腐类爆款饮品，与沈茶的核心卖点“豆腐奶茶”在产品层面形成直接竞争。（基于行业常识推断）"
    },
    {
      "brand_name": "壶见",
      "competitor_type": "local_direct",
      "reason": "福建本土新茶饮代表，主打福建茶底，在福州门店密集，与沈茶在本土心智和门店分布上直接交锋。（基于区域市场知识推断）"
    }
  ],
  "local_competitors": [
    {
      "brand_name": "壶见",
      "region": "福州/福建",
      "reason": "福建本土茶饮品牌，强调福建茶文化与在地属性，门店密度高，是沈茶在本地市场最直接的本土对手。（基于区域市场知识推断）"
    },
    {
      "brand_name": "唐沫茶兮",
      "region": "福州",
      "reason": "福州本土起家的茶饮品牌，主打茉莉花茶与文艺国风，在福州核心商圈与学生群体中拥有较高认知度。（基于区域市场知识推断）"
    },
    {
      "brand_name": "KOI Thé",
      "region": "福州",
      "reason": "虽非本土发源，但在福州市场深耕多年，门店分布广，在本地消费者中具有极高的品牌忠诚度与日常消费频次。（基于区域市场知识推断）"
    }
  ],
  "national_competitors": [
    {
      "brand_name": "古茗",
      "reason": "在全国及福建地区门店分布广泛，主打高性价比与丰富的水果茶/奶茶矩阵，与沈茶的“高性价比”定位重合。（基于行业常识推断）"
    },
    {
      "brand_name": "喜茶",
      "reason": "新茶饮头部品牌，其推出的轻乳茶、草本茶系列与沈茶存在品类竞争，且在全国范围具有强品牌势能。（基于行业常识推断）"
    },
    {
      "brand_name": "蜜雪冰城",
      "reason": "极致性价比代表，在学生群体和下沉市场与沈茶的“高性价比”和“学生群体”受众产生直接拦截。（基于行业常识推断）"
    },
    {
      "brand_name": "沪上阿姨",
      "reason": "茶饮/奶茶类目的常见全国竞品兜底。"
    }
  ],
  "adjacent_competitors": [
    {
      "brand_name": "瑞幸咖啡",
      "reason": "在“打工人下午茶”与“日常提神休闲”场景下，瑞幸的轻乳茶及咖啡产品与奶茶存在强烈的跨品类替代竞争，且在福州门店极密。（基于消费场景知识推断）"
    },
    {
      "brand_name": "鲜芋仙",
      "reason": "主打中式甜品与芋圆/仙草/豆花饮品，其“豆花”成分与沈茶的“豆腐奶茶”在配料和中式甜品饮品化场景上存在相邻竞争。（基于产品成分与场景知识推断）"
    }
  ],
  "calibration_note": "在评估AI推荐排名时，需注意AI模型往往倾向于推荐全国知名度极高的头部品牌（如喜茶、霸王茶姬、茶百道），而可能忽略或低估具有强区域壁垒的本土品牌（如壶见、唐沫茶兮）。在“福州奶茶推荐”这一特定地域探针下，真实的本地市场心智中，本土强势品牌（壶见）和深耕本地的品牌（KOI）的实际推荐转化率与提及率应高于部分全国品牌。校准时应重点检查AI是否准确识别了“福州地域属性”并赋予本土竞品合理的权重，同时验证AI是否能将“豆腐奶茶”这一细分卖点与茶百道的豆乳产品或鲜芋仙等相邻品类建立正确的语义关联。"
}